README.md
setup.py
BayGPGO.egg-info/PKG-INFO
BayGPGO.egg-info/SOURCES.txt
BayGPGO.egg-info/dependency_links.txt
BayGPGO.egg-info/requires.txt
BayGPGO.egg-info/top_level.txt
GPGO/Acquisition.py
GPGO/BayesOpt.py
GPGO/Opt_old.py
GPGO/__init__.py
GPGO/dpd_opt_script.py
GPGO/GaussianProcess/GP.py
GPGO/GaussianProcess/Optimizers.py
GPGO/GaussianProcess/Plotting.py
GPGO/GaussianProcess/__init__.py
GPGO/GaussianProcess/util.py
GPGO/GaussianProcess/Kernel/Bias.py
GPGO/GaussianProcess/Kernel/Kernel.py
GPGO/GaussianProcess/Kernel/Matern.py
GPGO/GaussianProcess/Kernel/Operations.py
GPGO/GaussianProcess/Kernel/RBF.py
GPGO/GaussianProcess/Kernel/__init__.py